odmf/__init__.py
odmf/config.py
odmf/jobmail.py
odmf/odmf.py
odmf/dataimport/__init__.py
odmf/dataimport/base.py
odmf/dataimport/importlog.py
odmf/dataimport/pandas_import.py
odmf/db/__init__.py
odmf/db/base.py
odmf/db/dataset.py
odmf/db/image.py
odmf/db/job.py
odmf/db/person.py
odmf/db/project.py
odmf/db/projection.py
odmf/db/site.py
odmf/db/timeseries.py
odmf/db/transformed_timeseries.py
odmf/db/sql/drop_cuahsi.sql
odmf/db/sql/tables/censorcodecv.sql
odmf/db/sql/tables/configuration.sql
odmf/db/sql/tables/datacollectionmethod.sql
odmf/db/sql/tables/dataset.sql
odmf/db/sql/tables/datasource.sql
odmf/db/sql/tables/datatypecv.sql
odmf/db/sql/tables/generalcategorycv.sql
odmf/db/sql/tables/image.sql
odmf/db/sql/tables/installation.sql
odmf/db/sql/tables/job.sql
odmf/db/sql/tables/log.sql
odmf/db/sql/tables/offsettypes.sql
odmf/db/sql/tables/person.sql
odmf/db/sql/tables/project.sql
odmf/db/sql/tables/quality.sql
odmf/db/sql/tables/record.sql
odmf/db/sql/tables/samplemediumcv.sql
odmf/db/sql/tables/samples.sql
odmf/db/sql/tables/sampletypecv.sql
odmf/db/sql/tables/seriescatalog_counts.sql
odmf/db/sql/tables/site.sql
odmf/db/sql/tables/sitetypecv.sql
odmf/db/sql/tables/speciationcv.sql
odmf/db/sql/tables/topiccategorycv.sql
odmf/db/sql/tables/transformed_timeseries.sql
odmf/db/sql/tables/transforms.sql
odmf/db/sql/tables/units.sql
odmf/db/sql/tables/valuetype.sql
odmf/db/sql/tables/valuetypecv.sql
odmf/db/sql/tables/variablenamecv.sql
odmf/db/sql/tables/verticaldatumcv.sql
odmf/db/sql/views/_variables.sql
odmf/db/sql/views/datavalues.sql
odmf/db/sql/views/methods.sql
odmf/db/sql/views/qualitycontrollevels.sql
odmf/db/sql/views/sbo_odm_invalid_datasets.sql
odmf/db/sql/views/sbo_odm_invalid_valuetypes.sql
odmf/db/sql/views/series.sql
odmf/db/sql/views/seriescatalog.sql
odmf/db/sql/views/sites.sql
odmf/db/sql/views/sources.sql
odmf/db/sql/views/spatialreferences.sql
odmf/db/sql/views/variables.sql
odmf/migration_util/adds_person_and_config.sql
odmf-2022.11.14.dist-info/LICENSE
odmf-2022.11.14.dist-info/METADATA
odmf-2022.11.14.dist-info/WHEEL
odmf-2022.11.14.dist-info/entry_points.txt
odmf-2022.11.14.dist-info/top_level.txt
odmf-2022.11.14.dist-info/RECORD
