Metadata-Version: 2.1
Name: odmf
Version: 2022.11.14
Summary: Observatory Data Management Framework
Home-page: https://github.com/jlu-ilr-hydro/odmf
Author: Philipp Kraft
Author-email: philipp.kraft@umwelt.uni-giessen.de
License: UNKNOWN
Platform: UNKNOWN
Requires-Python: >=3.8
License-File: LICENSE
Requires-Dist: setuptools (>=39.0)
Requires-Dist: wheel (>=0.30)
Requires-Dist: chardet
Requires-Dist: PyYAML (>=5.1)
Requires-Dist: Pillow (~=9.1.0)
Requires-Dist: cherrypy (>=18.0.0)
Requires-Dist: kajiki (~=0.9.0)
Requires-Dist: markdown
Requires-Dist: matplotlib (<3.6.0,>=3.5.0)
Requires-Dist: pandas (~=1.4.0)
Requires-Dist: scipy (~=1.8.0)
Requires-Dist: xlrd (==2.0.1)
Requires-Dist: numba (>=0.50.0)
Requires-Dist: openpyxl (>=3.0.7)
Requires-Dist: asteval (>=0.9.25)
Requires-Dist: pyarrow (~=8.0.0)
Requires-Dist: psycopg2-binary
Requires-Dist: pytz (==2022.1)
Requires-Dist: sqlalchemy (~=1.4.0)
Requires-Dist: bcrypt
Requires-Dist: bleach (>=3.1.0)
Requires-Dist: click (>=7.0)
Requires-Dist: humanize
Requires-Dist: plotly (==5.6.0)
Requires-Dist: kaleido
Requires-Dist: ipython (>=8.0.1)
Requires-Dist: requests
Requires-Dist: pytest
Requires-Dist: pytest-postgresql
Requires-Dist: coverage
Requires-Dist: lxml
Requires-Dist: coloredlogs
